{
  "machines": [
    1,
    2,
    3
  ],
  "workpieces": [
    {
      "name": "Workpiece1",
      "optional_machines": [
        [
          1,
          2,
          3
        ],
        [
          1,
          2
        ],
        [
          1,
          2
        ]
      ],
      "processing_time": [
        [
          12,
          10,
          11
        ],
        [
          11,
          8
        ],
        [
          13,
          13
        ]
      ]
    },
    {
      "name": "Workpiece2",
      "optional_machines": [
        [
          2,
          3
        ],
        [
          1,
          2
        ],
        [
          1,
          2,
          3
        ],
        [
          1,
          2,
          3
        ]
      ],
      "processing_time": [
        [
          15,
          11
        ],
        [
          9,
          15
        ],
        [
          11,
          12,
          9
        ],
        [
          15,
          13,
          11
        ]
      ]
    },
    {
      "name": "Workpiece3",
      "optional_machines": [
        [
          1,
          2,
          3
        ],
        [
          1,
          2
        ],
        [
          1,
          2
        ]
      ],
      "processing_time": [
        [
          15,
          10,
          14
        ],
        [
          13,
          12
        ],
        [
          10,
          14
        ]
      ]
    }
  ]
}