{
  "machines": [
    1,
    2,
    3
  ],
  "workpieces": [
    {
      "name": "Workpiece1",
      "optional_machines": [
        [
          1,
          2,
          3
        ],
        [
          1,
          2,
          3
        ],
        [
          2,
          3
        ],
        [
          1,
          2,
          3
        ],
        [
          1,
          2,
          3
        ],
        [
          1,
          2,
          3
        ]
      ],
      "processing_time": [
        [
          13,
          10,
          16
        ],
        [
          18,
          15,
          6
        ],
        [
          20,
          11
        ],
        [
          15,
          5,
          11
        ],
        [
          13,
          20,
          13
        ],
        [
          16,
          16,
          5
        ]
      ]
    },
    {
      "name": "Workpiece2",
      "optional_machines": [
        [
          2
        ],
        [
          1,
          2
        ],
        [
          1,
          2,
          3
        ]
      ],
      "processing_time": [
        [
          14
        ],
        [
          16,
          6
        ],
        [
          16,
          14,
          19
        ]
      ]
    },
    {
      "name": "Workpiece3",
      "optional_machines": [
        [
          1,
          2,
          3
        ],
        [
          2,
          3
        ],
        [
          2
        ],
        [
          1,
          2,
          3
        ],
        [
          2
        ],
        [
          1,
          2,
          3
        ],
        [
          2,
          3
        ]
      ],
      "processing_time": [
        [
          5,
          18,
          7
        ],
        [
          13,
          11
        ],
        [
          16
        ],
        [
          9,
          19,
          15
        ],
        [
          9
        ],
        [
          18,
          12,
          19
        ],
        [
          17,
          19
        ]
      ]
    },
    {
      "name": "Workpiece4",
      "optional_machines": [
        [
          1
        ],
        [
          1,
          2,
          3
        ],
        [
          2
        ]
      ],
      "processing_time": [
        [
          6
        ],
        [
          17,
          6,
          15
        ],
        [
          15
        ]
      ]
    }
  ]
}