{
  "machines": [
    1,
    2,
    3
  ],
  "workpieces": [
    {
      "name": "Workpiece1",
      "optional_machines": [
        [
          1,
          2,
          3
        ],
        [
          2,
          3
        ],
        [
          1,
          2,
          3
        ],
        [
          3
        ],
        [
          1,
          2,
          3
        ]
      ],
      "processing_time": [
        [
          18,
          9,
          10
        ],
        [
          10,
          11
        ],
        [
          14,
          16,
          13
        ],
        [
          15
        ],
        [
          19,
          20,
          18
        ]
      ]
    },
    {
      "name": "Workpiece2",
      "optional_machines": [
        [
          1
        ],
        [
          1,
          2
        ],
        [
          2,
          3
        ]
      ],
      "processing_time": [
        [
          15
        ],
        [
          20,
          18
        ],
        [
          8,
          18
        ]
      ]
    },
    {
      "name": "Workpiece3",
      "optional_machines": [
        [
          2,
          3
        ],
        [
          3
        ],
        [
          1,
          2,
          3
        ],
        [
          3
        ],
        [
          1,
          2,
          3
        ]
      ],
      "processing_time": [
        [
          20,
          18
        ],
        [
          8
        ],
        [
          7,
          19,
          5
        ],
        [
          9
        ],
        [
          6,
          6,
          10
        ]
      ]
    },
    {
      "name": "Workpiece4",
      "optional_machines": [
        [
          1
        ],
        [
          1,
          2,
          3
        ],
        [
          3
        ],
        [
          1,
          2,
          3
        ]
      ],
      "processing_time": [
        [
          17
        ],
        [
          19,
          18,
          18
        ],
        [
          15
        ],
        [
          5,
          18,
          12
        ]
      ]
    }
  ]
}