{
  "machines": [
    1,
    2,
    3
  ],
  "workpieces": [
    {
      "name": "Workpiece1",
      "optional_machines": [
        [
          1,
          2,
          3
        ],
        [
          3
        ],
        [
          1
        ],
        [
          2
        ],
        [
          1,
          2
        ],
        [
          1,
          2,
          3
        ],
        [
          1,
          2,
          3
        ]
      ],
      "processing_time": [
        [
          20,
          5,
          8
        ],
        [
          12
        ],
        [
          11
        ],
        [
          19
        ],
        [
          14,
          13
        ],
        [
          6,
          18,
          5
        ],
        [
          9,
          15,
          20
        ]
      ]
    },
    {
      "name": "Workpiece2",
      "optional_machines": [
        [
          1
        ],
        [
          1,
          2,
          3
        ],
        [
          2,
          3
        ]
      ],
      "processing_time": [
        [
          9
        ],
        [
          19,
          16,
          7
        ],
        [
          20,
          19
        ]
      ]
    },
    {
      "name": "Workpiece3",
      "optional_machines": [
        [
          2,
          3
        ],
        [
          1,
          2,
          3
        ],
        [
          3
        ],
        [
          1,
          2,
          3
        ],
        [
          1,
          2,
          3
        ]
      ],
      "processing_time": [
        [
          5,
          12
        ],
        [
          17,
          16,
          11
        ],
        [
          5
        ],
        [
          14,
          10,
          20
        ],
        [
          16,
          14,
          8
        ]
      ]
    },
    {
      "name": "Workpiece4",
      "optional_machines": [
        [
          1,
          2
        ],
        [
          3
        ],
        [
          1
        ]
      ],
      "processing_time": [
        [
          10,
          8
        ],
        [
          5
        ],
        [
          15
        ]
      ]
    }
  ]
}