{
  "machines": [
    1,
    2,
    3
  ],
  "workpieces": [
    {
      "name": "Workpiece1",
      "optional_machines": [
        [
          3
        ],
        [
          3
        ],
        [
          1,
          2,
          3
        ],
        [
          1,
          2,
          3
        ],
        [
          1,
          2,
          3
        ],
        [
          1,
          2,
          3
        ]
      ],
      "processing_time": [
        [
          14
        ],
        [
          14
        ],
        [
          20,
          5,
          5
        ],
        [
          16,
          16,
          13
        ],
        [
          17,
          15,
          13
        ],
        [
          7,
          9,
          5
        ]
      ]
    },
    {
      "name": "Workpiece2",
      "optional_machines": [
        [
          1,
          2,
          3
        ],
        [
          2,
          3
        ],
        [
          3
        ],
        [
          2,
          3
        ],
        [
          1
        ]
      ],
      "processing_time": [
        [
          16,
          12,
          15
        ],
        [
          17,
          5
        ],
        [
          18
        ],
        [
          17,
          18
        ],
        [
          10
        ]
      ]
    },
    {
      "name": "Workpiece3",
      "optional_machines": [
        [
          1
        ],
        [
          1,
          2,
          3
        ],
        [
          1
        ],
        [
          2
        ],
        [
          2,
          3
        ],
        [
          3
        ],
        [
          1
        ]
      ],
      "processing_time": [
        [
          11
        ],
        [
          11,
          11,
          9
        ],
        [
          9
        ],
        [
          16
        ],
        [
          20,
          13
        ],
        [
          9
        ],
        [
          9
        ]
      ]
    },
    {
      "name": "Workpiece4",
      "optional_machines": [
        [
          1,
          2,
          3
        ],
        [
          2
        ],
        [
          1,
          2
        ],
        [
          1
        ],
        [
          2
        ]
      ],
      "processing_time": [
        [
          8,
          10,
          8
        ],
        [
          8
        ],
        [
          14,
          20
        ],
        [
          9
        ],
        [
          9
        ]
      ]
    },
    {
      "name": "Workpiece5",
      "optional_machines": [
        [
          1,
          2,
          3
        ],
        [
          2
        ],
        [
          2,
          3
        ],
        [
          2
        ],
        [
          1,
          2,
          3
        ]
      ],
      "processing_time": [
        [
          7,
          15,
          5
        ],
        [
          10
        ],
        [
          8,
          20
        ],
        [
          13
        ],
        [
          19,
          17,
          18
        ]
      ]
    }
  ]
}